pnlogger/__init__.py
pnlogger/logger.py
pnlogger-1.0.4.dist-info/WHEEL
pnlogger-1.0.4.dist-info/METADATA
pnlogger-1.0.4.dist-info/RECORD
