Metadata-Version: 2.1
Name: pnlogger
Version: 1.0.4
Summary: Im taking this line only.... not below line
Author-email: Pradeep <nair.pradeep@gmail.com>
Classifier: License :: OSI Approved :: Apache Software License
